qcode/__init__.py
qcode/flasklog.py
qcode_mystuff-0.0.2.dist-info/licenses/LICENSE
qcode_mystuff-0.0.2.dist-info/METADATA
qcode_mystuff-0.0.2.dist-info/WHEEL
qcode_mystuff-0.0.2.dist-info/top_level.txt
qcode_mystuff-0.0.2.dist-info/RECORD
