Metadata-Version: 2.4
Name: qcode-mystuff
Version: 0.0.2
Summary: Module for useful funcion that regular python should have
Author: Quantung
Author-email: quantungplayer@gmail.com
License-File: LICENSE
Dynamic: author
Dynamic: author-email
Dynamic: license-file
Dynamic: summary
